[
  {
    "py/object": "model.contact.Contact",
    "aday": "(//option[@value='-'])[2]",
    "address": "",
    "address2": "",
    "all_emails_from_home_page": null,
    "all_phones_from_home_page": null,
    "amonth": "(//option[@value='-'])[2]",
    "ayear": "",
    "bday": "//option[@value='-']",
    "bmonth": "//option[@value='-']",
    "byear": "",
    "company": "",
    "email": "",
    "email2": "",
    "email3": "",
    "fax": "",
    "firstname": "",
    "home": "",
    "homepage": "",
    "id": null,
    "lastname": "",
    "middlename": "",
    "mobile": "",
    "nickname": "",
    "notes": "",
    "phone2": "",
    "title": "",
    "work": ""
  },
  {
    "py/object": "model.contact.Contact",
    "aday": "(//option[@value='4'])[2]",
    "address": "address1azIgtos M7XH cLphC",
    "address2": "address2fP Ay X rpzR7rD",
    "all_emails_from_home_page": null,
    "all_phones_from_home_page": null,
    "amonth": "(//option[@value='November'])[2]",
    "ayear": "ay",
    "bday": "//option[@value='12']",
    "bmonth": "//option[@value='October']",
    "byear": "by",
    "company": "companyetV6R iS7H rv0A4l",
    "email": "emailwv2 GyTGMEArGLb R",
    "email2": "email2vqVtUAE",
    "email3": "email3 JlUgMEB4bQcQ",
    "fax": "fax",
    "firstname": "firstnamed0ii",
    "home": "homeDKKkGU",
    "homepage": "email9c",
    "id": null,
    "lastname": "lastname6jV ZRA",
    "middlename": "middlenameyRY3 WYn",
    "mobile": "mobilek V",
    "nickname": "nicknames5ekEM",
    "notes": "notes Bwu lhy1 A8B",
    "phone2": "phone2g9",
    "title": "titlemM",
    "work": "work 8GYe"
  },
  {
    "py/object": "model.contact.Contact",
    "aday": "(//option[@value='11'])[2]",
    "address": "addressMGgz HMsW FR5aiL48UK9RR9q",
    "address2": "address2 7xi9bn z lsoDKq31",
    "all_emails_from_home_page": null,
    "all_phones_from_home_page": null,
    "amonth": "(//option[@value='August'])[2]",
    "ayear": "ay",
    "bday": "//option[@value='8']",
    "bmonth": "//option[@value='August']",
    "byear": "by8",
    "company": "company3",
    "email": "emailm1i",
    "email2": "email2",
    "email3": "email3 o",
    "fax": "fax 1Bj5PEkdDo",
    "firstname": "firstname1U CS09ga",
    "home": "homex1",
    "homepage": "emailD1 xzHRiPa8",
    "id": null,
    "lastname": "lastnameimwoEby",
    "middlename": "middlenamemgi7 AYV",
    "mobile": "mobileWt5qwDq",
    "nickname": "nickname Dn2ZrV",
    "notes": "notesxfbTVxlzh P bJj",
    "phone2": "phone2gwYFK1dHrTxy9",
    "title": "title dT7",
    "work": "worku5N x"
  },
  {
    "py/object": "model.contact.Contact",
    "aday": "(//option[@value='19'])[2]",
    "address": "addressnJL U1wifmrs",
    "address2": "address2 zpd5H2bDZLf",
    "all_emails_from_home_page": null,
    "all_phones_from_home_page": null,
    "amonth": "(//option[@value='May'])[2]",
    "ayear": "ay",
    "bday": "//option[@value='5']",
    "bmonth": "//option[@value='October']",
    "byear": "by2",
    "company": "company0 TTxZFe5g",
    "email": "emailGM R4W6Vk9DvJnGSy",
    "email2": "email2YtUjv jRMpL3",
    "email3": "email31qxM1R vt63Uuy",
    "fax": "faxTR",
    "firstname": "firstnamezHrj1ojG",
    "home": "home GEmv6",
    "homepage": "emailqs",
    "id": null,
    "lastname": "lastnamelt",
    "middlename": "middlenameoXr",
    "mobile": "mobilew3s",
    "nickname": "nicknamem",
    "notes": "notespf",
    "phone2": "phone2ZgZ 2jq8j",
    "title": "title",
    "work": "workGOo"
  },
  {
    "py/object": "model.contact.Contact",
    "aday": "(//option[@value='30'])[2]",
    "address": "addresstPy8TigiRb6qHKC1",
    "address2": "address2",
    "all_emails_from_home_page": null,
    "all_phones_from_home_page": null,
    "amonth": "(//option[@value='May'])[2]",
    "ayear": "ay5",
    "bday": "//option[@value='15']",
    "bmonth": "//option[@value='September']",
    "byear": "by",
    "company": "companyHiuaY bd a VvSh",
    "email": "email6 YNEaOy0",
    "email2": "email2f5c",
    "email3": "email3d1JFF",
    "fax": "faxWGSlbc1",
    "firstname": "firstnamer0W",
    "home": "homelEd",
    "homepage": "emailKD nY",
    "id": null,
    "lastname": "lastnamenOk",
    "middlename": "middlenameHr5r",
    "mobile": "mobileilQ7 7TQ4 5",
    "nickname": "nickname IYzAQX",
    "notes": "notesc J4ajHuzRJVq3gyI",
    "phone2": "phone2 kbxMa",
    "title": "titleb",
    "work": "work1"
  },
  {
    "py/object": "model.contact.Contact",
    "aday": "(//option[@value='22'])[2]",
    "address": "address3D6NMvRsff3s8C1H 21j uF",
    "address2": "address2 nVbqzi",
    "all_emails_from_home_page": null,
    "all_phones_from_home_page": null,
    "amonth": "(//option[@value='September'])[2]",
    "ayear": "ay",
    "bday": "//option[@value='6']",
    "bmonth": "//option[@value='February']",
    "byear": "bys",
    "company": "companyvueUO admwYu 0 l0iC7",
    "email": "email37Bclc",
    "email2": "email2C",
    "email3": "email3x9wY 5d",
    "fax": "fax7RY",
    "firstname": "firstname wnCu 1iF",
    "home": "home2ofNkdr",
    "homepage": "email6 M95K",
    "id": null,
    "lastname": "lastnamenvL3ItYMmZ",
    "middlename": "middlename9dchC9Hl",
    "mobile": "mobilefFYVY m",
    "nickname": "nicknameLi H 2",
    "notes": "notes",
    "phone2": "phone2tbZwW qTaR",
    "title": "titleQ OI",
    "work": "workh2ft5"
  }
]